cursedtodo-0.1.9.dist-info/METADATA
cursedtodo-0.1.9.dist-info/WHEEL
cursedtodo-0.1.9.dist-info/entry_points.txt
cursedtodo-0.1.9.dist-info/licenses/LICENCE
cursedtodo/__init__.py
cursedtodo/controlers/__init__.py
cursedtodo/controlers/base_controller.py
cursedtodo/controlers/edit_todo_controller.py
cursedtodo/controlers/main_controller.py
cursedtodo/controlers/view_todo_controller.py
cursedtodo/cursedtodo.py
cursedtodo/models/__init__.py
cursedtodo/models/todo.py
cursedtodo/models/todo_repository.py
cursedtodo/utils/__init__.py
cursedtodo/utils/config.py
cursedtodo/utils/editor.py
cursedtodo/utils/formater.py
cursedtodo/utils/router.py
cursedtodo/utils/selectinput.py
cursedtodo/utils/textinput.py
cursedtodo/utils/time.py
cursedtodo/utils/validator.py
cursedtodo/utils/window_utils.py
cursedtodo/views/__init__.py
cursedtodo/views/base_view.py
cursedtodo/views/dialog.py
cursedtodo/views/edit_todo_view.py
cursedtodo/views/form/Button.py
cursedtodo/views/form/__init__.py
cursedtodo/views/form/base_field.py
cursedtodo/views/form/categories_field.py
cursedtodo/views/form/datetime_field.py
cursedtodo/views/form/priority_field.py
cursedtodo/views/form/select_field.py
cursedtodo/views/form/textarea_field.py
cursedtodo/views/form/textinput_field.py
cursedtodo/views/main_view.py
cursedtodo/views/view_todo_view.py
cursedtodo-0.1.9.dist-info/RECORD
