Metadata-Version: 2.1
Name: cursedtodo
Version: 0.1.9
Summary: Default template for PDM package
Author-Email: =?utf-8?b?RnJhbsOnb2lzIExhY2jDqHNl?= <francois.lachese@gmail.com>
License: MIT
Requires-Python: >=3.12
Requires-Dist: ics>=0.7.2
